[
    {
        "יישוב": "עולש",
        "מספר פניות": 2810,
        "זמן טיפול ממוצע": 40.1106217614,
        "סטיית תקן זמן טיפול": 64.4502093112,
        "אחוז חריגות": 40.9964412811
    },
    {
        "יישוב": "בית הלוי",
        "מספר פניות": 1464,
        "זמן טיפול ממוצע": 42.7788617305,
        "סטיית תקן זמן טיפול": 93.593099881,
        "אחוז חריגות": 40.8469945355
    },
    {
        "יישוב": "כפר חיים",
        "מספר פניות": 1355,
        "זמן טיפול ממוצע": 34.7851677018,
        "סטיית תקן זמן טיפול": 59.6574152507,
        "אחוז חריגות": 40.0
    },
    {
        "יישוב": "הדר עם",
        "מספר פניות": 1473,
        "זמן טיפול ממוצע": 36.3872691774,
        "סטיית תקן זמן טיפול": 57.2279023899,
        "אחוז חריגות": 39.9185336049
    },
    {
        "יישוב": "נעורים",
        "מספר פניות": 764,
        "זמן טיפול ממוצע": 41.0641292944,
        "סטיית תקן זמן טיפול": 87.2527694384,
        "אחוז חריגות": 39.6596858639
    },
    {
        "יישוב": "גבעת חיים (איחוד)",
        "מספר פניות": 1722,
        "זמן טיפול ממוצע": 36.5000113209,
        "סטיית תקן זמן טיפול": 61.1984594545,
        "אחוז חריגות": 39.6051103368
    },
    {
        "יישוב": "אלישיב",
        "מספר פניות": 1571,
        "זמן טיפול ממוצע": 32.9294794445,
        "סטיית תקן זמן טיפול": 52.7405964662,
        "אחוז חריגות": 39.3380012731
    },
    {
        "יישוב": "מבואות ים",
        "מספר פניות": 56,
        "זמן טיפול ממוצע": 41.5359144091,
        "סטיית תקן זמן טיפול": 62.3674047223,
        "אחוז חריגות": 39.2857142857
    },
    {
        "יישוב": "בארותיים",
        "מספר פניות": 3073,
        "זמן טיפול ממוצע": 35.8753568381,
        "סטיית תקן זמן טיפול": 62.2418978998,
        "אחוז חריגות": 39.2775789131
    },
    {
        "יישוב": "עין החורש",
        "מספר פניות": 775,
        "זמן טיפול ממוצע": 39.9190382563,
        "סטיית תקן זמן טיפול": 77.1718621087,
        "אחוז חריגות": 38.8387096774
    },
    {
        "יישוב": "חבצלת השרון",
        "מספר פניות": 1189,
        "זמן טיפול ממוצע": 40.5786784452,
        "סטיית תקן זמן טיפול": 63.0955919718,
        "אחוז חריגות": 38.7720773759
    },
    {
        "יישוב": "כפר מונאש",
        "מספר פניות": 2409,
        "זמן טיפול ממוצע": 41.2961841011,
        "סטיית תקן זמן טיפול": 81.1096811213,
        "אחוז חריגות": 38.7297633873
    },
    {
        "יישוב": "בית יצחק-שער חפר",
        "מספר פניות": 4106,
        "זמן טיפול ממוצע": 36.6872241587,
        "סטיית תקן זמן טיפול": 62.49050845,
        "אחוז חריגות": 38.6751095957
    },
    {
        "יישוב": "העוגן",
        "מספר פניות": 1426,
        "זמן טיפול ממוצע": 36.3918891255,
        "סטיית תקן זמן טיפול": 72.1377575462,
        "אחוז חריגות": 38.5694249649
    },
    {
        "יישוב": "גן יאשיה",
        "מספר פניות": 2711,
        "זמן טיפול ממוצע": 35.5771995855,
        "סטיית תקן זמן טיפול": 69.5177387218,
        "אחוז חריגות": 38.4360014755
    },
    {
        "יישוב": "אביחיל",
        "מספר פניות": 2330,
        "זמן טיפול ממוצע": 35.6929441967,
        "סטיית תקן זמן טיפול": 62.8197615195,
        "אחוז חריגות": 38.3261802575
    },
    {
        "יישוב": "שושנת העמקים",
        "מספר פניות": 2455,
        "זמן טיפול ממוצע": 38.3220816378,
        "סטיית תקן זמן טיפול": 95.7713093685,
        "אחוז חריגות": 38.2892057026
    },
    {
        "יישוב": "פארק תעשיות עמק חפר",
        "מספר פניות": 2328,
        "זמן טיפול ממוצע": 35.943693774,
        "סטיית תקן זמן טיפול": 60.4010485133,
        "אחוז חריגות": 38.1872852234
    },
    {
        "יישוב": "חרב לאת",
        "מספר פניות": 1369,
        "זמן טיפול ממוצע": 32.2213897232,
        "סטיית תקן זמן טיפול": 50.4786573138,
        "אחוז חריגות": 37.9839298758
    },
    {
        "יישוב": "ביתן אהרון",
        "מספר פניות": 798,
        "זמן טיפול ממוצע": 39.1951207422,
        "סטיית תקן זמן טיפול": 79.5349982341,
        "אחוז חריגות": 37.969924812
    },
    {
        "יישוב": "גבעת שפירא",
        "מספר פניות": 560,
        "זמן טיפול ממוצע": 32.584192846,
        "סטיית תקן זמן טיפול": 47.0684447012,
        "אחוז חריגות": 37.8571428571
    },
    {
        "יישוב": "צוקי ים",
        "מספר פניות": 1976,
        "זמן טיפול ממוצע": 36.1596766361,
        "סטיית תקן זמן טיפול": 62.7405038919,
        "אחוז חריגות": 37.8036437247
    },
    {
        "יישוב": "חניאל",
        "מספר פניות": 1652,
        "זמן טיפול ממוצע": 32.008613099,
        "סטיית תקן זמן טיפול": 50.1628431441,
        "אחוז חריגות": 37.7118644068
    },
    {
        "יישוב": "בית ינאי",
        "מספר פניות": 1311,
        "זמן טיפול ממוצע": 33.1540056943,
        "סטיית תקן זמן טיפול": 53.6713494975,
        "אחוז חריגות": 37.6048817696
    },
    {
        "יישוב": "בת חן",
        "מספר פניות": 1027,
        "זמן טיפול ממוצע": 33.3674359976,
        "סטיית תקן זמן טיפול": 48.3369866193,
        "אחוז חריגות": 37.4878286271
    },
    {
        "יישוב": "כפר ויתקין",
        "מספר פניות": 4774,
        "זמן טיפול ממוצע": 40.5355058966,
        "סטיית תקן זמן טיפול": 78.1497219174,
        "אחוז חריגות": 37.4319229158
    },
    {
        "יישוב": "בית חירות",
        "מספר פניות": 2407,
        "זמן טיפול ממוצע": 32.752649646,
        "סטיית תקן זמן טיפול": 50.5849933695,
        "אחוז חריגות": 37.3909430827
    },
    {
        "יישוב": "בת חפר",
        "מספר פניות": 12223,
        "זמן טיפול ממוצע": 35.329386682,
        "סטיית תקן זמן טיפול": 63.5561234866,
        "אחוז חריגות": 37.3148981428
    },
    {
        "יישוב": "חופית",
        "מספר פניות": 2358,
        "זמן טיפול ממוצע": 34.2314882453,
        "סטיית תקן זמן טיפול": 51.8609696105,
        "אחוז חריגות": 37.1501272265
    },
    {
        "יישוב": "בחן",
        "מספר פניות": 2299,
        "זמן טיפול ממוצע": 33.5085182133,
        "סטיית תקן זמן טיפול": 51.4994109655,
        "אחוז חריגות": 37.1030882993
    },
    {
        "יישוב": "המעפיל",
        "מספר פניות": 1100,
        "זמן טיפול ממוצע": 34.7281540523,
        "סטיית תקן זמן טיפול": 62.8333241733,
        "אחוז חריגות": 37.0909090909
    },
    {
        "יישוב": "כפר חוגלה",
        "מספר פניות": 1186,
        "זמן טיפול ממוצע": 33.2615132969,
        "סטיית תקן זמן טיפול": 49.8658173117,
        "אחוז חריגות": 36.9308600337
    },
    {
        "יישוב": "יד חנה",
        "מספר פניות": 1941,
        "זמן טיפול ממוצע": 31.1829368971,
        "סטיית תקן זמן טיפול": 48.3951861208,
        "אחוז חריגות": 36.7851622875
    },
    {
        "יישוב": "משמר השרון",
        "מספר פניות": 562,
        "זמן טיפול ממוצע": 37.3493906301,
        "סטיית תקן זמן טיפול": 55.0965816331,
        "אחוז חריגות": 36.6548042705
    },
    {
        "יישוב": "מעברות",
        "מספר פניות": 623,
        "זמן טיפול ממוצע": 30.4068678213,
        "סטיית תקן זמן טיפול": 45.0037328766,
        "אחוז חריגות": 36.2760834671
    },
    {
        "יישוב": "מכמורת",
        "מספר פניות": 4499,
        "זמן טיפול ממוצע": 35.2675213494,
        "סטיית תקן זמן טיפול": 69.7173431807,
        "אחוז חריגות": 36.2525005557
    },
    {
        "יישוב": "אחיטוב",
        "מספר פניות": 2664,
        "זמן טיפול ממוצע": 31.2574027957,
        "סטיית תקן זמן טיפול": 53.6722346721,
        "אחוז חריגות": 36.036036036
    },
    {
        "יישוב": "כפר הרא\"ה",
        "מספר פניות": 1628,
        "זמן טיפול ממוצע": 36.8848524028,
        "סטיית תקן זמן טיפול": 70.96134526,
        "אחוז חריגות": 35.6265356265
    },
    {
        "יישוב": "בורגתה",
        "מספר פניות": 2082,
        "זמן טיפול ממוצע": 33.7468629819,
        "סטיית תקן זמן טיפול": 56.3862163446,
        "אחוז חריגות": 35.590778098
    },
    {
        "יישוב": "כפר ידידיה",
        "מספר פניות": 1028,
        "זמן טיפול ממוצע": 34.0298813909,
        "סטיית תקן זמן טיפול": 57.3364413198,
        "אחוז חריגות": 35.1167315175
    },
    {
        "יישוב": "מדרשת רופין",
        "מספר פניות": 233,
        "זמן טיפול ממוצע": 40.2128019609,
        "סטיית תקן זמן טיפול": 84.9270773809,
        "אחוז חריגות": 34.7639484979
    },
    {
        "יישוב": "גאולי תימן",
        "מספר פניות": 812,
        "זמן טיפול ממוצע": 34.2070916597,
        "סטיית תקן זמן טיפול": 50.1260366633,
        "אחוז חריגות": 34.7290640394
    },
    {
        "יישוב": "גבעת חיים (מאוחד)",
        "מספר פניות": 500,
        "זמן טיפול ממוצע": 36.550351129,
        "סטיית תקן זמן טיפול": 50.4804027139,
        "אחוז חריגות": 34.4
    },
    {
        "יישוב": "חיבת ציון",
        "מספר פניות": 1873,
        "זמן טיפול ממוצע": 32.8230007851,
        "סטיית תקן זמן טיפול": 55.0374310634,
        "אחוז חריגות": 33.3689268553
    },
    {
        "יישוב": "אומץ",
        "מספר פניות": 1160,
        "זמן טיפול ממוצע": 29.5914241942,
        "סטיית תקן זמן טיפול": 48.363981996,
        "אחוז חריגות": 33.3620689655
    },
    {
        "יישוב": "בניין המועצה",
        "מספר פניות": 45,
        "זמן טיפול ממוצע": 44.3347418099,
        "סטיית תקן זמן טיפול": 51.686886845,
        "אחוז חריגות": 28.8888888889
    },
    {
        "יישוב": "לא תושב המועצה",
        "מספר פניות": 8189,
        "זמן טיפול ממוצע": 35.2799829014,
        "סטיית תקן זמן טיפול": 80.4649797761,
        "אחוז חריגות": 21.8952253022
    }
]